ecidacli/__init__.py
ecidacli/docker_interface.py
ecidacli/ecida-templates/.gitignore
ecidacli/ecida-templates/__init__.py
ecidacli/ecida-templates/module.py
ecidacli/ecida-templates/namespace.yaml
ecidacli/ecida-templates/requirements.txt
ecidacli-0.1.29.dist-info/METADATA
ecidacli-0.1.29.dist-info/WHEEL
ecidacli-0.1.29.dist-info/entry_points.txt
ecidacli-0.1.29.dist-info/top_level.txt
ecidacli-0.1.29.dist-info/RECORD
