Metadata-Version: 2.4
Name: ecidacli
Version: 0.1.29
Summary: The ECiDA CLI for Python to make things easier.
Author-email: Mostafa Hadadian <hadadian@caidel.com>
License-Expression: MIT
Project-URL: homepage, https://gitlab.com/ecida
Classifier: Operating System :: OS Independent
Requires-Python: >=3.11
Requires-Dist: pyyaml
Requires-Dist: setuptools
Requires-Dist: importlib-metadata
Requires-Dist: packaging
Requires-Dist: kafka-python
Requires-Dist: requests
